tensorweaver/__init__.py
tensorweaver/autodiff/function.py
tensorweaver/autodiff/helpers.py
tensorweaver/autodiff/topological_sort.py
tensorweaver/autodiff/variable.py
tensorweaver/autograd/__init__.py
tensorweaver/layers/__init__.py
tensorweaver/layers/dropout.py
tensorweaver/layers/embedding.py
tensorweaver/layers/layer.py
tensorweaver/layers/layer_dict.py
tensorweaver/layers/layer_list.py
tensorweaver/layers/layer_norm.py
tensorweaver/layers/linear.py
tensorweaver/layers/multihead_attention.py
tensorweaver/losses/__init__.py
tensorweaver/losses/mse.py
tensorweaver/nn/__init__.py
tensorweaver/nn/functional/__init__.py
tensorweaver/onnx/README.md
tensorweaver/onnx/__init__.py
tensorweaver/onnx/onnx_program.py
tensorweaver/onnx/ops/__init__.py
tensorweaver/onnx/ops/add.py
tensorweaver/onnx/ops/matmul.py
tensorweaver/onnx/registry.py
tensorweaver/onnx/utils/__init__.py
tensorweaver/onnx/utils/name_manager.py
tensorweaver/onnx/utils/registry.py
tensorweaver/onnx/utils/type_mapper.py
tensorweaver/operators/__init__.py
tensorweaver/operators/add.py
tensorweaver/operators/argmax.py
tensorweaver/operators/broadcast_to.py
tensorweaver/operators/cat.py
tensorweaver/operators/cos.py
tensorweaver/operators/cross_entropy.py
tensorweaver/operators/div.py
tensorweaver/operators/dropout.py
tensorweaver/operators/embedding.py
tensorweaver/operators/eq.py
tensorweaver/operators/exp.py
tensorweaver/operators/faltten.py
tensorweaver/operators/gelu.py
tensorweaver/operators/getitem.py
tensorweaver/operators/layer_norm.py
tensorweaver/operators/log_softmax.py
tensorweaver/operators/lt.py
tensorweaver/operators/masked_fill.py
tensorweaver/operators/matmul.py
tensorweaver/operators/max.py
tensorweaver/operators/mean.py
tensorweaver/operators/mul.py
tensorweaver/operators/multinomial.py
tensorweaver/operators/neg.py
tensorweaver/operators/nll_loss.py
tensorweaver/operators/permute.py
tensorweaver/operators/pow.py
tensorweaver/operators/power.py
tensorweaver/operators/relu.py
tensorweaver-0.0.3.dist-info/LICENSE
tensorweaver-0.0.3.dist-info/METADATA
tensorweaver-0.0.3.dist-info/WHEEL
tensorweaver-0.0.3.dist-info/RECORD
