Metadata-Version: 2.3
Name: tensorweaver
Version: 0.0.3
Summary: A modern educational deep learning framework for students, engineers and researchers
License: MIT
Author: Xiaoquan Kong
Author-email: u1mail2me@gmail.com
Requires-Python: >=3.9,<3.13
Classifier: License :: OSI Approved :: MIT License
Classifier: Programming Language :: Python :: 3
Classifier: Programming Language :: Python :: 3.9
Classifier: Programming Language :: Python :: 3.10
Classifier: Programming Language :: Python :: 3.11
Classifier: Programming Language :: Python :: 3.12
Requires-Dist: numpy (>=1.24.0,<2.0.0)
Requires-Dist: onnx (>=1.17.0,<2.0.0)
Requires-Dist: typeguard (>=4.4.2,<5.0.0)
